[
  {
    "id": "k01",
    "type": "normal",
    "speaker": "Kâhin",
    "text": "Sence ışık bana da döner mi bir gün?",
    "options": [
      {
        "text": "Umut ediyorum, cevaplar hep gecikir.",
        "effects": {
          "faith": 6,
          "trust": 4,
          "hostility": 0
        }
      },
      {
        "text": "Belki... ama bazen yol bizden kaçar.",
        "effects": {
          "faith": 4,
          "trust": 2,
          "hostility": 1
        }
      },
      {
        "text": "Kimin umurunda, artık beklemiyorum.",
        "effects": {
          "faith": 0,
          "trust": -1,
          "hostility": 5
        }
      }
    ]
  },
  {
    "id": "k02",
    "type": "normal",
    "speaker": "Kâhin",
    "text": "Karanlığın sonu gerçekten var mı?",
    "options": [
      {
        "text": "İnançla yaşarsan, evet.",
        "effects": {
          "faith": 7,
          "trust": 4,
          "hostility": 0
        }
      },
      {
        "text": "Karanlık uzun ama geçer.",
        "effects": {
          "faith": 5,
          "trust": 3,
          "hostility": 1
        }
      },
      {
        "text": "Yeterince bekleyince her şey anlamsız olur.",
        "effects": {
          "faith": 1,
          "trust": 0,
          "hostility": 4
        }
      }
    ]
  },
  {
    "id": "k03",
    "type": "normal",
    "speaker": "Kâhin",
    "text": "Kalbimdeki bu yük hafifler mi zamanla?",
    "options": [
      {
        "text": "Her yük zamanla şekil değiştirir.",
        "effects": {
          "faith": 5,
          "trust": 4,
          "hostility": 0
        }
      },
      {
        "text": "Yük seninle konuşuyorsa dinle.",
        "effects": {
          "faith": 3,
          "trust": 2,
          "hostility": 1
        }
      },
      {
        "text": "Bazı yükler sonsuza dek kalır.",
        "effects": {
          "faith": 1,
          "trust": 1,
          "hostility": 3
        }
      }
    ]
  },
  {
    "id": "k04",
    "type": "normal",
    "speaker": "Kâhin",
    "text": "Tanrı hâlâ bizi duyuyor mu sence?",
    "options": [
      {
        "text": "Umut ediyorum, cevaplar hep gecikir.",
        "effects": {
          "faith": 6,
          "trust": 4,
          "hostility": 0
        }
      },
      {
        "text": "Belki... ama bazen yol bizden kaçar.",
        "effects": {
          "faith": 4,
          "trust": 2,
          "hostility": 1
        }
      },
      {
        "text": "Kimin umurunda, artık beklemiyorum.",
        "effects": {
          "faith": 0,
          "trust": -1,
          "hostility": 5
        }
      }
    ]
  },
  {
    "id": "k05",
    "type": "normal",
    "speaker": "Kâhin",
    "text": "Benim için de bir yol var mı hâlâ?",
    "options": [
      {
        "text": "İnançla yaşarsan, evet.",
        "effects": {
          "faith": 7,
          "trust": 4,
          "hostility": 0
        }
      },
      {
        "text": "Karanlık uzun ama geçer.",
        "effects": {
          "faith": 5,
          "trust": 3,
          "hostility": 1
        }
      },
      {
        "text": "Yeterince bekleyince her şey anlamsız olur.",
        "effects": {
          "faith": 1,
          "trust": 0,
          "hostility": 4
        }
      }
    ]
  },
  {
    "id": "k06",
    "type": "normal",
    "speaker": "Kâhin",
    "text": "İçimdeki boşluk dolacak mı bir gün?",
    "options": [
      {
        "text": "Her yük zamanla şekil değiştirir.",
        "effects": {
          "faith": 5,
          "trust": 4,
          "hostility": 0
        }
      },
      {
        "text": "Yük seninle konuşuyorsa dinle.",
        "effects": {
          "faith": 3,
          "trust": 2,
          "hostility": 1
        }
      },
      {
        "text": "Bazı yükler sonsuza dek kalır.",
        "effects": {
          "faith": 1,
          "trust": 1,
          "hostility": 3
        }
      }
    ]
  },
  {
    "id": "k07",
    "type": "normal",
    "speaker": "Kâhin",
    "text": "Kayıp olan geri döner mi, kahin?",
    "options": [
      {
        "text": "Umut ediyorum, cevaplar hep gecikir.",
        "effects": {
          "faith": 6,
          "trust": 4,
          "hostility": 0
        }
      },
      {
        "text": "Belki... ama bazen yol bizden kaçar.",
        "effects": {
          "faith": 4,
          "trust": 2,
          "hostility": 1
        }
      },
      {
        "text": "Kimin umurunda, artık beklemiyorum.",
        "effects": {
          "faith": 0,
          "trust": -1,
          "hostility": 5
        }
      }
    ]
  },
  {
    "id": "k08",
    "type": "normal",
    "speaker": "Kâhin",
    "text": "Ben de affedilebilir miyim?",
    "options": [
      {
        "text": "İnançla yaşarsan, evet.",
        "effects": {
          "faith": 7,
          "trust": 4,
          "hostility": 0
        }
      },
      {
        "text": "Karanlık uzun ama geçer.",
        "effects": {
          "faith": 5,
          "trust": 3,
          "hostility": 1
        }
      },
      {
        "text": "Yeterince bekleyince her şey anlamsız olur.",
        "effects": {
          "faith": 1,
          "trust": 0,
          "hostility": 4
        }
      }
    ]
  },
  {
    "id": "k09",
    "type": "normal",
    "speaker": "Kâhin",
    "text": "Uykularım artık huzurlu olur mu?",
    "options": [
      {
        "text": "Her yük zamanla şekil değiştirir.",
        "effects": {
          "faith": 5,
          "trust": 4,
          "hostility": 0
        }
      },
      {
        "text": "Yük seninle konuşuyorsa dinle.",
        "effects": {
          "faith": 3,
          "trust": 2,
          "hostility": 1
        }
      },
      {
        "text": "Bazı yükler sonsuza dek kalır.",
        "effects": {
          "faith": 1,
          "trust": 1,
          "hostility": 3
        }
      }
    ]
  },
  {
    "id": "k10",
    "type": "normal",
    "speaker": "Kâhin",
    "text": "Bu savaş bir gün bitecek mi?",
    "options": [
      {
        "text": "Umut ediyorum, cevaplar hep gecikir.",
        "effects": {
          "faith": 6,
          "trust": 4,
          "hostility": 0
        }
      },
      {
        "text": "Belki... ama bazen yol bizden kaçar.",
        "effects": {
          "faith": 4,
          "trust": 2,
          "hostility": 1
        }
      },
      {
        "text": "Kimin umurunda, artık beklemiyorum.",
        "effects": {
          "faith": 0,
          "trust": -1,
          "hostility": 5
        }
      }
    ]
  },
  {
    "id": "k11",
    "type": "normal",
    "speaker": "Kâhin",
    "text": "Kalbim neden hâlâ korkuyor?",
    "options": [
      {
        "text": "İnançla yaşarsan, evet.",
        "effects": {
          "faith": 7,
          "trust": 4,
          "hostility": 0
        }
      },
      {
        "text": "Karanlık uzun ama geçer.",
        "effects": {
          "faith": 5,
          "trust": 3,
          "hostility": 1
        }
      },
      {
        "text": "Yeterince bekleyince her şey anlamsız olur.",
        "effects": {
          "faith": 1,
          "trust": 0,
          "hostility": 4
        }
      }
    ]
  },
  {
    "id": "k12",
    "type": "normal",
    "speaker": "Kâhin",
    "text": "Rüyalarımda gördüğüm ışık, gerçek mi?",
    "options": [
      {
        "text": "Her yük zamanla şekil değiştirir.",
        "effects": {
          "faith": 5,
          "trust": 4,
          "hostility": 0
        }
      },
      {
        "text": "Yük seninle konuşuyorsa dinle.",
        "effects": {
          "faith": 3,
          "trust": 2,
          "hostility": 1
        }
      },
      {
        "text": "Bazı yükler sonsuza dek kalır.",
        "effects": {
          "faith": 1,
          "trust": 1,
          "hostility": 3
        }
      }
    ]
  },
  {
    "id": "k13",
    "type": "normal",
    "speaker": "Kâhin",
    "text": "Kendimi yeniden bulabilir miyim?",
    "options": [
      {
        "text": "Umut ediyorum, cevaplar hep gecikir.",
        "effects": {
          "faith": 6,
          "trust": 4,
          "hostility": 0
        }
      },
      {
        "text": "Belki... ama bazen yol bizden kaçar.",
        "effects": {
          "faith": 4,
          "trust": 2,
          "hostility": 1
        }
      },
      {
        "text": "Kimin umurunda, artık beklemiyorum.",
        "effects": {
          "faith": 0,
          "trust": -1,
          "hostility": 5
        }
      }
    ]
  },
  {
    "id": "k14",
    "type": "normal",
    "speaker": "Kâhin",
    "text": "Sessizlik cevap olabilir mi bazen?",
    "options": [
      {
        "text": "İnançla yaşarsan, evet.",
        "effects": {
          "faith": 7,
          "trust": 4,
          "hostility": 0
        }
      },
      {
        "text": "Karanlık uzun ama geçer.",
        "effects": {
          "faith": 5,
          "trust": 3,
          "hostility": 1
        }
      },
      {
        "text": "Yeterince bekleyince her şey anlamsız olur.",
        "effects": {
          "faith": 1,
          "trust": 0,
          "hostility": 4
        }
      }
    ]
  },
  {
    "id": "k15",
    "type": "normal",
    "speaker": "Kâhin",
    "text": "Yolumu kaybettim... yönü nasıl bulurum?",
    "options": [
      {
        "text": "Her yük zamanla şekil değiştirir.",
        "effects": {
          "faith": 5,
          "trust": 4,
          "hostility": 0
        }
      },
      {
        "text": "Yük seninle konuşuyorsa dinle.",
        "effects": {
          "faith": 3,
          "trust": 2,
          "hostility": 1
        }
      },
      {
        "text": "Bazı yükler sonsuza dek kalır.",
        "effects": {
          "faith": 1,
          "trust": 1,
          "hostility": 3
        }
      }
    ]
  },
  {
    "id": "k16",
    "type": "normal",
    "speaker": "Kâhin",
    "text": "Gece neden bu kadar uzun geliyor?",
    "options": [
      {
        "text": "Umut ediyorum, cevaplar hep gecikir.",
        "effects": {
          "faith": 6,
          "trust": 4,
          "hostility": 0
        }
      },
      {
        "text": "Belki... ama bazen yol bizden kaçar.",
        "effects": {
          "faith": 4,
          "trust": 2,
          "hostility": 1
        }
      },
      {
        "text": "Kimin umurunda, artık beklemiyorum.",
        "effects": {
          "faith": 0,
          "trust": -1,
          "hostility": 5
        }
      }
    ]
  },
  {
    "id": "k17",
    "type": "normal",
    "speaker": "Kâhin",
    "text": "Ben de ışığı hak ediyor muyum?",
    "options": [
      {
        "text": "İnançla yaşarsan, evet.",
        "effects": {
          "faith": 7,
          "trust": 4,
          "hostility": 0
        }
      },
      {
        "text": "Karanlık uzun ama geçer.",
        "effects": {
          "faith": 5,
          "trust": 3,
          "hostility": 1
        }
      },
      {
        "text": "Yeterince bekleyince her şey anlamsız olur.",
        "effects": {
          "faith": 1,
          "trust": 0,
          "hostility": 4
        }
      }
    ]
  },
  {
    "id": "k18",
    "type": "normal",
    "speaker": "Kâhin",
    "text": "Gözyaşlarım kuruyacak mı bir gün?",
    "options": [
      {
        "text": "Her yük zamanla şekil değiştirir.",
        "effects": {
          "faith": 5,
          "trust": 4,
          "hostility": 0
        }
      },
      {
        "text": "Yük seninle konuşuyorsa dinle.",
        "effects": {
          "faith": 3,
          "trust": 2,
          "hostility": 1
        }
      },
      {
        "text": "Bazı yükler sonsuza dek kalır.",
        "effects": {
          "faith": 1,
          "trust": 1,
          "hostility": 3
        }
      }
    ]
  },
  {
    "id": "k19",
    "type": "normal",
    "speaker": "Kâhin",
    "text": "Sevdiğim biri beni hâlâ bekliyor olabilir mi?",
    "options": [
      {
        "text": "Umut ediyorum, cevaplar hep gecikir.",
        "effects": {
          "faith": 6,
          "trust": 4,
          "hostility": 0
        }
      },
      {
        "text": "Belki... ama bazen yol bizden kaçar.",
        "effects": {
          "faith": 4,
          "trust": 2,
          "hostility": 1
        }
      },
      {
        "text": "Kimin umurunda, artık beklemiyorum.",
        "effects": {
          "faith": 0,
          "trust": -1,
          "hostility": 5
        }
      }
    ]
  },
  {
    "id": "k20",
    "type": "normal",
    "speaker": "Kâhin",
    "text": "Kalbimin sesi hâlâ doğruyu söylüyor mu?",
    "options": [
      {
        "text": "İnançla yaşarsan, evet.",
        "effects": {
          "faith": 7,
          "trust": 4,
          "hostility": 0
        }
      },
      {
        "text": "Karanlık uzun ama geçer.",
        "effects": {
          "faith": 5,
          "trust": 3,
          "hostility": 1
        }
      },
      {
        "text": "Yeterince bekleyince her şey anlamsız olur.",
        "effects": {
          "faith": 1,
          "trust": 0,
          "hostility": 4
        }
      }
    ]
  },
  {
    "id": "k21",
    "type": "normal",
    "speaker": "Kâhin",
    "text": "Tanrı sessiz kaldığında ne yapmalıyız?",
    "options": [
      {
        "text": "Her yük zamanla şekil değiştirir.",
        "effects": {
          "faith": 5,
          "trust": 4,
          "hostility": 0
        }
      },
      {
        "text": "Yük seninle konuşuyorsa dinle.",
        "effects": {
          "faith": 3,
          "trust": 2,
          "hostility": 1
        }
      },
      {
        "text": "Bazı yükler sonsuza dek kalır.",
        "effects": {
          "faith": 1,
          "trust": 1,
          "hostility": 3
        }
      }
    ]
  },
  {
    "id": "k22",
    "type": "normal",
    "speaker": "Kâhin",
    "text": "Kaybolmuş olan kaderimi tekrar bulabilir miyim?",
    "options": [
      {
        "text": "Umut ediyorum, cevaplar hep gecikir.",
        "effects": {
          "faith": 6,
          "trust": 4,
          "hostility": 0
        }
      },
      {
        "text": "Belki... ama bazen yol bizden kaçar.",
        "effects": {
          "faith": 4,
          "trust": 2,
          "hostility": 1
        }
      },
      {
        "text": "Kimin umurunda, artık beklemiyorum.",
        "effects": {
          "faith": 0,
          "trust": -1,
          "hostility": 5
        }
      }
    ]
  },
  {
    "id": "k23",
    "type": "normal",
    "speaker": "Kâhin",
    "text": "Beni anlayan bir ruh kaldı mı bu dünyada?",
    "options": [
      {
        "text": "İnançla yaşarsan, evet.",
        "effects": {
          "faith": 7,
          "trust": 4,
          "hostility": 0
        }
      },
      {
        "text": "Karanlık uzun ama geçer.",
        "effects": {
          "faith": 5,
          "trust": 3,
          "hostility": 1
        }
      },
      {
        "text": "Yeterince bekleyince her şey anlamsız olur.",
        "effects": {
          "faith": 1,
          "trust": 0,
          "hostility": 4
        }
      }
    ]
  },
  {
    "id": "k24",
    "type": "normal",
    "speaker": "Kâhin",
    "text": "Yalnızlık, bir sınav mı yoksa ceza mı?",
    "options": [
      {
        "text": "Her yük zamanla şekil değiştirir.",
        "effects": {
          "faith": 5,
          "trust": 4,
          "hostility": 0
        }
      },
      {
        "text": "Yük seninle konuşuyorsa dinle.",
        "effects": {
          "faith": 3,
          "trust": 2,
          "hostility": 1
        }
      },
      {
        "text": "Bazı yükler sonsuza dek kalır.",
        "effects": {
          "faith": 1,
          "trust": 1,
          "hostility": 3
        }
      }
    ]
  },
  {
    "id": "k25",
    "type": "normal",
    "speaker": "Kâhin",
    "text": "Sessizliğin ardında umut var mı?",
    "options": [
      {
        "text": "Umut ediyorum, cevaplar hep gecikir.",
        "effects": {
          "faith": 6,
          "trust": 4,
          "hostility": 0
        }
      },
      {
        "text": "Belki... ama bazen yol bizden kaçar.",
        "effects": {
          "faith": 4,
          "trust": 2,
          "hostility": 1
        }
      },
      {
        "text": "Kimin umurunda, artık beklemiyorum.",
        "effects": {
          "faith": 0,
          "trust": -1,
          "hostility": 5
        }
      }
    ]
  },
  {
    "id": "k26",
    "type": "normal",
    "speaker": "Kâhin",
    "text": "İnançsız geçen yıllarımı telafi edebilir miyim?",
    "options": [
      {
        "text": "İnançla yaşarsan, evet.",
        "effects": {
          "faith": 7,
          "trust": 4,
          "hostility": 0
        }
      },
      {
        "text": "Karanlık uzun ama geçer.",
        "effects": {
          "faith": 5,
          "trust": 3,
          "hostility": 1
        }
      },
      {
        "text": "Yeterince bekleyince her şey anlamsız olur.",
        "effects": {
          "faith": 1,
          "trust": 0,
          "hostility": 4
        }
      }
    ]
  },
  {
    "id": "k27",
    "type": "normal",
    "speaker": "Kâhin",
    "text": "Yıkılmış olanı yeniden inşa etmek mümkün mü?",
    "options": [
      {
        "text": "Her yük zamanla şekil değiştirir.",
        "effects": {
          "faith": 5,
          "trust": 4,
          "hostility": 0
        }
      },
      {
        "text": "Yük seninle konuşuyorsa dinle.",
        "effects": {
          "faith": 3,
          "trust": 2,
          "hostility": 1
        }
      },
      {
        "text": "Bazı yükler sonsuza dek kalır.",
        "effects": {
          "faith": 1,
          "trust": 1,
          "hostility": 3
        }
      }
    ]
  },
  {
    "id": "k28",
    "type": "normal",
    "speaker": "Kâhin",
    "text": "Gelecek neden bu kadar belirsiz görünüyor?",
    "options": [
      {
        "text": "Umut ediyorum, cevaplar hep gecikir.",
        "effects": {
          "faith": 6,
          "trust": 4,
          "hostility": 0
        }
      },
      {
        "text": "Belki... ama bazen yol bizden kaçar.",
        "effects": {
          "faith": 4,
          "trust": 2,
          "hostility": 1
        }
      },
      {
        "text": "Kimin umurunda, artık beklemiyorum.",
        "effects": {
          "faith": 0,
          "trust": -1,
          "hostility": 5
        }
      }
    ]
  },
  {
    "id": "k29",
    "type": "normal",
    "speaker": "Kâhin",
    "text": "Kalbimdeki gölgeyi nasıl aydınlatırım?",
    "options": [
      {
        "text": "İnançla yaşarsan, evet.",
        "effects": {
          "faith": 7,
          "trust": 4,
          "hostility": 0
        }
      },
      {
        "text": "Karanlık uzun ama geçer.",
        "effects": {
          "faith": 5,
          "trust": 3,
          "hostility": 1
        }
      },
      {
        "text": "Yeterince bekleyince her şey anlamsız olur.",
        "effects": {
          "faith": 1,
          "trust": 0,
          "hostility": 4
        }
      }
    ]
  },
  {
    "id": "k30",
    "type": "normal",
    "speaker": "Kâhin",
    "text": "Sonsuzluk korkutucu mu, yoksa kurtarıcı mı?",
    "options": [
      {
        "text": "Her yük zamanla şekil değiştirir.",
        "effects": {
          "faith": 5,
          "trust": 4,
          "hostility": 0
        }
      },
      {
        "text": "Yük seninle konuşuyorsa dinle.",
        "effects": {
          "faith": 3,
          "trust": 2,
          "hostility": 1
        }
      },
      {
        "text": "Bazı yükler sonsuza dek kalır.",
        "effects": {
          "faith": 1,
          "trust": 1,
          "hostility": 3
        }
      }
    ]
  },
  {
    "id": "k31",
    "type": "normal",
    "speaker": "Kâhin",
    "text": "Sonsuz karanlıktan sonra gerçekten bir şafak gelir mi?",
    "options": [
      {
        "text": "Umut ediyorum, cevaplar hep gecikir.",
        "effects": {
          "faith": 6,
          "trust": 4,
          "hostility": 0
        }
      },
      {
        "text": "Belki... ama bazen yol bizden kaçar.",
        "effects": {
          "faith": 4,
          "trust": 2,
          "hostility": 1
        }
      },
      {
        "text": "Kimin umurunda, artık beklemiyorum.",
        "effects": {
          "faith": 0,
          "trust": -1,
          "hostility": 5
        }
      }
    ]
  },
  {
    "id": "k32",
    "type": "normal",
    "speaker": "Kâhin",
    "text": "Kendimi affetmem mümkün mü sence?",
    "options": [
      {
        "text": "İnançla yaşarsan, evet.",
        "effects": {
          "faith": 7,
          "trust": 4,
          "hostility": 0
        }
      },
      {
        "text": "Karanlık uzun ama geçer.",
        "effects": {
          "faith": 5,
          "trust": 3,
          "hostility": 1
        }
      },
      {
        "text": "Yeterince bekleyince her şey anlamsız olur.",
        "effects": {
          "faith": 1,
          "trust": 0,
          "hostility": 4
        }
      }
    ]
  },
  {
    "id": "k33",
    "type": "normal",
    "speaker": "Kâhin",
    "text": "Kırık bir kalp yeniden atabilir mi?",
    "options": [
      {
        "text": "Her yük zamanla şekil değiştirir.",
        "effects": {
          "faith": 5,
          "trust": 4,
          "hostility": 0
        }
      },
      {
        "text": "Yük seninle konuşuyorsa dinle.",
        "effects": {
          "faith": 3,
          "trust": 2,
          "hostility": 1
        }
      },
      {
        "text": "Bazı yükler sonsuza dek kalır.",
        "effects": {
          "faith": 1,
          "trust": 1,
          "hostility": 3
        }
      }
    ]
  },
  {
    "id": "k34",
    "type": "normal",
    "speaker": "Kâhin",
    "text": "İçimdeki sessiz çığlıkları kim duyar?",
    "options": [
      {
        "text": "Umut ediyorum, cevaplar hep gecikir.",
        "effects": {
          "faith": 6,
          "trust": 4,
          "hostility": 0
        }
      },
      {
        "text": "Belki... ama bazen yol bizden kaçar.",
        "effects": {
          "faith": 4,
          "trust": 2,
          "hostility": 1
        }
      },
      {
        "text": "Kimin umurunda, artık beklemiyorum.",
        "effects": {
          "faith": 0,
          "trust": -1,
          "hostility": 5
        }
      }
    ]
  },
  {
    "id": "k35",
    "type": "normal",
    "speaker": "Kâhin",
    "text": "Geçmişimi geride bırakabilir miyim?",
    "options": [
      {
        "text": "İnançla yaşarsan, evet.",
        "effects": {
          "faith": 7,
          "trust": 4,
          "hostility": 0
        }
      },
      {
        "text": "Karanlık uzun ama geçer.",
        "effects": {
          "faith": 5,
          "trust": 3,
          "hostility": 1
        }
      },
      {
        "text": "Yeterince bekleyince her şey anlamsız olur.",
        "effects": {
          "faith": 1,
          "trust": 0,
          "hostility": 4
        }
      }
    ]
  },
  {
    "id": "k36",
    "type": "normal",
    "speaker": "Kâhin",
    "text": "Yıldızlara bakmak hâlâ bir anlam taşır mı?",
    "options": [
      {
        "text": "Her yük zamanla şekil değiştirir.",
        "effects": {
          "faith": 5,
          "trust": 4,
          "hostility": 0
        }
      },
      {
        "text": "Yük seninle konuşuyorsa dinle.",
        "effects": {
          "faith": 3,
          "trust": 2,
          "hostility": 1
        }
      },
      {
        "text": "Bazı yükler sonsuza dek kalır.",
        "effects": {
          "faith": 1,
          "trust": 1,
          "hostility": 3
        }
      }
    ]
  },
  {
    "id": "k37",
    "type": "normal",
    "speaker": "Kâhin",
    "text": "Sence de yollar bitmiyor mu artık?",
    "options": [
      {
        "text": "Umut ediyorum, cevaplar hep gecikir.",
        "effects": {
          "faith": 6,
          "trust": 4,
          "hostility": 0
        }
      },
      {
        "text": "Belki... ama bazen yol bizden kaçar.",
        "effects": {
          "faith": 4,
          "trust": 2,
          "hostility": 1
        }
      },
      {
        "text": "Kimin umurunda, artık beklemiyorum.",
        "effects": {
          "faith": 0,
          "trust": -1,
          "hostility": 5
        }
      }
    ]
  },
  {
    "id": "k38",
    "type": "normal",
    "speaker": "Kâhin",
    "text": "Bir gün gülümsemek kolaylaşır mı?",
    "options": [
      {
        "text": "İnançla yaşarsan, evet.",
        "effects": {
          "faith": 7,
          "trust": 4,
          "hostility": 0
        }
      },
      {
        "text": "Karanlık uzun ama geçer.",
        "effects": {
          "faith": 5,
          "trust": 3,
          "hostility": 1
        }
      },
      {
        "text": "Yeterince bekleyince her şey anlamsız olur.",
        "effects": {
          "faith": 1,
          "trust": 0,
          "hostility": 4
        }
      }
    ]
  },
  {
    "id": "k39",
    "type": "normal",
    "speaker": "Kâhin",
    "text": "Acılarla yaşamak mı, yoksa unutmak mı daha iyidir?",
    "options": [
      {
        "text": "Her yük zamanla şekil değiştirir.",
        "effects": {
          "faith": 5,
          "trust": 4,
          "hostility": 0
        }
      },
      {
        "text": "Yük seninle konuşuyorsa dinle.",
        "effects": {
          "faith": 3,
          "trust": 2,
          "hostility": 1
        }
      },
      {
        "text": "Bazı yükler sonsuza dek kalır.",
        "effects": {
          "faith": 1,
          "trust": 1,
          "hostility": 3
        }
      }
    ]
  },
  {
    "id": "k40",
    "type": "normal",
    "speaker": "Kâhin",
    "text": "Kalbimde hâlâ umut varsa... yeterli olur mu?",
    "options": [
      {
        "text": "Umut ediyorum, cevaplar hep gecikir.",
        "effects": {
          "faith": 6,
          "trust": 4,
          "hostility": 0
        }
      },
      {
        "text": "Belki... ama bazen yol bizden kaçar.",
        "effects": {
          "faith": 4,
          "trust": 2,
          "hostility": 1
        }
      },
      {
        "text": "Kimin umurunda, artık beklemiyorum.",
        "effects": {
          "faith": 0,
          "trust": -1,
          "hostility": 5
        }
      }
    ]
  },
  {
    "id": "k41",
    "type": "normal",
    "speaker": "Kâhin",
    "text": "Sana inansam, kendime de inanabilir miyim?",
    "options": [
      {
        "text": "İnançla yaşarsan, evet.",
        "effects": {
          "faith": 7,
          "trust": 4,
          "hostility": 0
        }
      },
      {
        "text": "Karanlık uzun ama geçer.",
        "effects": {
          "faith": 5,
          "trust": 3,
          "hostility": 1
        }
      },
      {
        "text": "Yeterince bekleyince her şey anlamsız olur.",
        "effects": {
          "faith": 1,
          "trust": 0,
          "hostility": 4
        }
      }
    ]
  },
  {
    "id": "k42",
    "type": "normal",
    "speaker": "Kâhin",
    "text": "Karanlıktan çıkmak için ışığı mı aramalıyım, yoksa içimde mi yanmalı?",
    "options": [
      {
        "text": "Her yük zamanla şekil değiştirir.",
        "effects": {
          "faith": 5,
          "trust": 4,
          "hostility": 0
        }
      },
      {
        "text": "Yük seninle konuşuyorsa dinle.",
        "effects": {
          "faith": 3,
          "trust": 2,
          "hostility": 1
        }
      },
      {
        "text": "Bazı yükler sonsuza dek kalır.",
        "effects": {
          "faith": 1,
          "trust": 1,
          "hostility": 3
        }
      }
    ]
  },
  {
    "id": "k43",
    "type": "normal",
    "speaker": "Kâhin",
    "text": "Tanrı neden susar, en çok ihtiyacımız olduğunda?",
    "options": [
      {
        "text": "Umut ediyorum, cevaplar hep gecikir.",
        "effects": {
          "faith": 6,
          "trust": 4,
          "hostility": 0
        }
      },
      {
        "text": "Belki... ama bazen yol bizden kaçar.",
        "effects": {
          "faith": 4,
          "trust": 2,
          "hostility": 1
        }
      },
      {
        "text": "Kimin umurunda, artık beklemiyorum.",
        "effects": {
          "faith": 0,
          "trust": -1,
          "hostility": 5
        }
      }
    ]
  },
  {
    "id": "k44",
    "type": "normal",
    "speaker": "Kâhin",
    "text": "Sence hayat bir döngü mü, yoksa düz bir çizgi mi?",
    "options": [
      {
        "text": "İnançla yaşarsan, evet.",
        "effects": {
          "faith": 7,
          "trust": 4,
          "hostility": 0
        }
      },
      {
        "text": "Karanlık uzun ama geçer.",
        "effects": {
          "faith": 5,
          "trust": 3,
          "hostility": 1
        }
      },
      {
        "text": "Yeterince bekleyince her şey anlamsız olur.",
        "effects": {
          "faith": 1,
          "trust": 0,
          "hostility": 4
        }
      }
    ]
  },
  {
    "id": "k45",
    "type": "normal",
    "speaker": "Kâhin",
    "text": "Zaman her yarayı sarar mı gerçekten?",
    "options": [
      {
        "text": "Her yük zamanla şekil değiştirir.",
        "effects": {
          "faith": 5,
          "trust": 4,
          "hostility": 0
        }
      },
      {
        "text": "Yük seninle konuşuyorsa dinle.",
        "effects": {
          "faith": 3,
          "trust": 2,
          "hostility": 1
        }
      },
      {
        "text": "Bazı yükler sonsuza dek kalır.",
        "effects": {
          "faith": 1,
          "trust": 1,
          "hostility": 3
        }
      }
    ]
  },
  {
    "id": "k46",
    "type": "normal",
    "speaker": "Kâhin",
    "text": "Neden hep ben kaybeden oluyorum, kahin?",
    "options": [
      {
        "text": "Umut ediyorum, cevaplar hep gecikir.",
        "effects": {
          "faith": 6,
          "trust": 4,
          "hostility": 0
        }
      },
      {
        "text": "Belki... ama bazen yol bizden kaçar.",
        "effects": {
          "faith": 4,
          "trust": 2,
          "hostility": 1
        }
      },
      {
        "text": "Kimin umurunda, artık beklemiyorum.",
        "effects": {
          "faith": 0,
          "trust": -1,
          "hostility": 5
        }
      }
    ]
  },
  {
    "id": "k47",
    "type": "normal",
    "speaker": "Kâhin",
    "text": "Adalet nerede kaldı bu topraklarda?",
    "options": [
      {
        "text": "İnançla yaşarsan, evet.",
        "effects": {
          "faith": 7,
          "trust": 4,
          "hostility": 0
        }
      },
      {
        "text": "Karanlık uzun ama geçer.",
        "effects": {
          "faith": 5,
          "trust": 3,
          "hostility": 1
        }
      },
      {
        "text": "Yeterince bekleyince her şey anlamsız olur.",
        "effects": {
          "faith": 1,
          "trust": 0,
          "hostility": 4
        }
      }
    ]
  },
  {
    "id": "k48",
    "type": "normal",
    "speaker": "Kâhin",
    "text": "Neden onlar yaşıyor da ben sürünüyorum?",
    "options": [
      {
        "text": "Her yük zamanla şekil değiştirir.",
        "effects": {
          "faith": 5,
          "trust": 4,
          "hostility": 0
        }
      },
      {
        "text": "Yük seninle konuşuyorsa dinle.",
        "effects": {
          "faith": 3,
          "trust": 2,
          "hostility": 1
        }
      },
      {
        "text": "Bazı yükler sonsuza dek kalır.",
        "effects": {
          "faith": 1,
          "trust": 1,
          "hostility": 3
        }
      }
    ]
  },
  {
    "id": "k49",
    "type": "normal",
    "speaker": "Kâhin",
    "text": "Kahrolası sessizlik neden bu kadar uzun sürdü?",
    "options": [
      {
        "text": "Umut ediyorum, cevaplar hep gecikir.",
        "effects": {
          "faith": 6,
          "trust": 4,
          "hostility": 0
        }
      },
      {
        "text": "Belki... ama bazen yol bizden kaçar.",
        "effects": {
          "faith": 4,
          "trust": 2,
          "hostility": 1
        }
      },
      {
        "text": "Kimin umurunda, artık beklemiyorum.",
        "effects": {
          "faith": 0,
          "trust": -1,
          "hostility": 5
        }
      }
    ]
  },
  {
    "id": "k50",
    "type": "normal",
    "speaker": "Kâhin",
    "text": "Tanrı neden sadece susuyor, bağırmamı mı bekliyor?",
    "options": [
      {
        "text": "İnançla yaşarsan, evet.",
        "effects": {
          "faith": 7,
          "trust": 4,
          "hostility": 0
        }
      },
      {
        "text": "Karanlık uzun ama geçer.",
        "effects": {
          "faith": 5,
          "trust": 3,
          "hostility": 1
        }
      },
      {
        "text": "Yeterince bekleyince her şey anlamsız olur.",
        "effects": {
          "faith": 1,
          "trust": 0,
          "hostility": 4
        }
      }
    ]
  },
  {
    "id": "k51",
    "type": "normal",
    "speaker": "Kâhin",
    "text": "Ne yaparsam yapayım, değişen bir şey olmuyor.",
    "options": [
      {
        "text": "Her yük zamanla şekil değiştirir.",
        "effects": {
          "faith": 5,
          "trust": 4,
          "hostility": 0
        }
      },
      {
        "text": "Yük seninle konuşuyorsa dinle.",
        "effects": {
          "faith": 3,
          "trust": 2,
          "hostility": 1
        }
      },
      {
        "text": "Bazı yükler sonsuza dek kalır.",
        "effects": {
          "faith": 1,
          "trust": 1,
          "hostility": 3
        }
      }
    ]
  },
  {
    "id": "k52",
    "type": "normal",
    "speaker": "Kâhin",
    "text": "Belki de kaderim böyleydi, değil mi?",
    "options": [
      {
        "text": "Umut ediyorum, cevaplar hep gecikir.",
        "effects": {
          "faith": 6,
          "trust": 4,
          "hostility": 0
        }
      },
      {
        "text": "Belki... ama bazen yol bizden kaçar.",
        "effects": {
          "faith": 4,
          "trust": 2,
          "hostility": 1
        }
      },
      {
        "text": "Kimin umurunda, artık beklemiyorum.",
        "effects": {
          "faith": 0,
          "trust": -1,
          "hostility": 5
        }
      }
    ]
  },
  {
    "id": "k53",
    "type": "normal",
    "speaker": "Kâhin",
    "text": "Savaşmaktan yoruldum. Durmak günah mı?",
    "options": [
      {
        "text": "İnançla yaşarsan, evet.",
        "effects": {
          "faith": 7,
          "trust": 4,
          "hostility": 0
        }
      },
      {
        "text": "Karanlık uzun ama geçer.",
        "effects": {
          "faith": 5,
          "trust": 3,
          "hostility": 1
        }
      },
      {
        "text": "Yeterince bekleyince her şey anlamsız olur.",
        "effects": {
          "faith": 1,
          "trust": 0,
          "hostility": 4
        }
      }
    ]
  },
  {
    "id": "k54",
    "type": "normal",
    "speaker": "Kâhin",
    "text": "Ben sadece kabul etmek istiyorum artık.",
    "options": [
      {
        "text": "Her yük zamanla şekil değiştirir.",
        "effects": {
          "faith": 5,
          "trust": 4,
          "hostility": 0
        }
      },
      {
        "text": "Yük seninle konuşuyorsa dinle.",
        "effects": {
          "faith": 3,
          "trust": 2,
          "hostility": 1
        }
      },
      {
        "text": "Bazı yükler sonsuza dek kalır.",
        "effects": {
          "faith": 1,
          "trust": 1,
          "hostility": 3
        }
      }
    ]
  },
  {
    "id": "k55",
    "type": "normal",
    "speaker": "Kâhin",
    "text": "İçimdeki direnç söndü. Bu normal mi, kahin?",
    "options": [
      {
        "text": "Umut ediyorum, cevaplar hep gecikir.",
        "effects": {
          "faith": 6,
          "trust": 4,
          "hostility": 0
        }
      },
      {
        "text": "Belki... ama bazen yol bizden kaçar.",
        "effects": {
          "faith": 4,
          "trust": 2,
          "hostility": 1
        }
      },
      {
        "text": "Kimin umurunda, artık beklemiyorum.",
        "effects": {
          "faith": 0,
          "trust": -1,
          "hostility": 5
        }
      }
    ]
  },
  {
    "id": "k56",
    "type": "normal",
    "speaker": "Kâhin",
    "text": "Peki ya her şey yalandıysa?",
    "options": [
      {
        "text": "İnançla yaşarsan, evet.",
        "effects": {
          "faith": 7,
          "trust": 4,
          "hostility": 0
        }
      },
      {
        "text": "Karanlık uzun ama geçer.",
        "effects": {
          "faith": 5,
          "trust": 3,
          "hostility": 1
        }
      },
      {
        "text": "Yeterince bekleyince her şey anlamsız olur.",
        "effects": {
          "faith": 1,
          "trust": 0,
          "hostility": 4
        }
      }
    ]
  },
  {
    "id": "k57",
    "type": "normal",
    "speaker": "Kâhin",
    "text": "Ya Tanrı diye konuşan bir hiçlikse?",
    "options": [
      {
        "text": "Her yük zamanla şekil değiştirir.",
        "effects": {
          "faith": 5,
          "trust": 4,
          "hostility": 0
        }
      },
      {
        "text": "Yük seninle konuşuyorsa dinle.",
        "effects": {
          "faith": 3,
          "trust": 2,
          "hostility": 1
        }
      },
      {
        "text": "Bazı yükler sonsuza dek kalır.",
        "effects": {
          "faith": 1,
          "trust": 1,
          "hostility": 3
        }
      }
    ]
  },
  {
    "id": "k58",
    "type": "normal",
    "speaker": "Kâhin",
    "text": "İnançsızlık bir lanet mi yoksa uyanış mı?",
    "options": [
      {
        "text": "Umut ediyorum, cevaplar hep gecikir.",
        "effects": {
          "faith": 6,
          "trust": 4,
          "hostility": 0
        }
      },
      {
        "text": "Belki... ama bazen yol bizden kaçar.",
        "effects": {
          "faith": 4,
          "trust": 2,
          "hostility": 1
        }
      },
      {
        "text": "Kimin umurunda, artık beklemiyorum.",
        "effects": {
          "faith": 0,
          "trust": -1,
          "hostility": 5
        }
      }
    ]
  },
  {
    "id": "k59",
    "type": "normal",
    "speaker": "Kâhin",
    "text": "Sen bile emin misin söylediklerinden?",
    "options": [
      {
        "text": "İnançla yaşarsan, evet.",
        "effects": {
          "faith": 7,
          "trust": 4,
          "hostility": 0
        }
      },
      {
        "text": "Karanlık uzun ama geçer.",
        "effects": {
          "faith": 5,
          "trust": 3,
          "hostility": 1
        }
      },
      {
        "text": "Yeterince bekleyince her şey anlamsız olur.",
        "effects": {
          "faith": 1,
          "trust": 0,
          "hostility": 4
        }
      }
    ]
  },
  {
    "id": "k60",
    "type": "normal",
    "speaker": "Kâhin",
    "text": "Yol göstermek senin görevin mi, yoksa aldatmak mı?",
    "options": [
      {
        "text": "Her yük zamanla şekil değiştirir.",
        "effects": {
          "faith": 5,
          "trust": 4,
          "hostility": 0
        }
      },
      {
        "text": "Yük seninle konuşuyorsa dinle.",
        "effects": {
          "faith": 3,
          "trust": 2,
          "hostility": 1
        }
      },
      {
        "text": "Bazı yükler sonsuza dek kalır.",
        "effects": {
          "faith": 1,
          "trust": 1,
          "hostility": 3
        }
      }
    ]
  }
]