{
  "mapType": "Varnan",
  "dialogues": [
    {
      "id": "varnan_01",
      "type": "normal",
      "speaker": "Varnan Gözcüsü",
      "text": "Varnan'ın gölgeleri seni izliyor. Neden geldin?",
      "options": [
        {
          "text": "Barış için geldim.",
          "effects": {
            "faith": 4,
            "trust": 3,
            "hostility": 0
          }
        },
        {
          "text": "Savaş için geldim.",
          "effects": {
            "faith": 2,
            "trust": 1,
            "hostility": 5
          }
        },
        {
          "text": "Sadece geçiyordum.",
          "effects": {
            "faith": 1,
            "trust": 2,
            "hostility": 1
          }
        }
      ]
    },
    {
      "id": "varnan_02",
      "type": "normal",
      "speaker": "Varnan Tüccarı",
      "text": "Bu topraklarda altın değil, bilgelik aranır.",
      "options": [
        {
          "text": "Bilgelik benim aradığım şey.",
          "effects": {
            "faith": 5,
            "trust": 4,
            "hostility": 0
          }
        },
        {
          "text": "Altın da fena olmaz.",
          "effects": {
            "faith": 2,
            "trust": 2,
            "hostility": 1
          }
        },
        {
          "text": "Hiçbir şey aramıyorum.",
          "effects": {
            "faith": 0,
            "trust": 0,
            "hostility": 2
          }
        }
      ]
    }
  ]
} 